{
  "states": [
    {
      "resourceType": "Location",
      "identifier": [
        {
          "system": "http://opencrvs.org/specs/id/statistical-code",
          "value": "ADMIN_STRUCTURE_AWn3s2RqgAN"
        },
        {
          "system": "http://opencrvs.org/specs/id/jurisdiction-type",
          "value": "STATE"
        }
      ],
      "name": "Central",
      "alias": [
        "Central"
      ],
      "description": "AWn3s2RqgAN",
      "status": "active",
      "mode": "instance",
      "partOf": {
        "reference": "Location/0"
      },
      "type": {
        "coding": [
          {
            "system": "http://opencrvs.org/specs/location-type",
            "code": "ADMIN_STRUCTURE"
          }
        ]
      },
      "physicalType": {
        "coding": [
          {
            "code": "jdn",
            "display": "Jurisdiction"
          }
        ]
      },
      "extension": [
        {
          "url": "http://hl7.org/fhir/StructureDefinition/location-boundary-geojson",
          "valueAttachment": {
            "contentType": "application/geo+json",
            "data": "<base64>"
          }
        }
      ],
      "id": "23d07b2f-3009-432a-98de-caa1f2958604"
    },
    {
      "resourceType": "Location",
      "identifier": [
        {
          "system": "http://opencrvs.org/specs/id/statistical-code",
          "value": "ADMIN_STRUCTURE_KozcEjeTyuD"
        },
        {
          "system": "http://opencrvs.org/specs/id/jurisdiction-type",
          "value": "STATE"
        }
      ],
      "name": "Sulaka",
      "alias": [
        "Sulaka"
      ],
      "description": "KozcEjeTyuD",
      "status": "active",
      "mode": "instance",
      "partOf": {
        "reference": "Location/0"
      },
      "type": {
        "coding": [
          {
            "system": "http://opencrvs.org/specs/location-type",
            "code": "ADMIN_STRUCTURE"
          }
        ]
      },
      "physicalType": {
        "coding": [
          {
            "code": "jdn",
            "display": "Jurisdiction"
          }
        ]
      },
      "extension": [
        {
          "url": "http://hl7.org/fhir/StructureDefinition/location-boundary-geojson",
          "valueAttachment": {
            "contentType": "application/geo+json",
            "data": "<base64>"
          }
        }
      ],
      "id": "cdcc74d5-148d-4408-9317-e04486f8dc15"
    },
    {
      "resourceType": "Location",
      "identifier": [
        {
          "system": "http://opencrvs.org/specs/id/statistical-code",
          "value": "ADMIN_STRUCTURE_B1u1bVtIA92"
        },
        {
          "system": "http://opencrvs.org/specs/id/jurisdiction-type",
          "value": "STATE"
        }
      ],
      "name": "Pualula",
      "alias": [
        "Pualula"
      ],
      "description": "B1u1bVtIA92",
      "status": "active",
      "mode": "instance",
      "partOf": {
        "reference": "Location/0"
      },
      "type": {
        "coding": [
          {
            "system": "http://opencrvs.org/specs/location-type",
            "code": "ADMIN_STRUCTURE"
          }
        ]
      },
      "physicalType": {
        "coding": [
          {
            "code": "jdn",
            "display": "Jurisdiction"
          }
        ]
      },
      "extension": [
        {
          "url": "http://hl7.org/fhir/StructureDefinition/location-boundary-geojson",
          "valueAttachment": {
            "contentType": "application/geo+json",
            "data": "<base64>"
          }
        }
      ],
      "id": "7d1d13b3-73fd-4e7a-ac93-a766a22b335a"
    },
    {
      "resourceType": "Location",
      "identifier": [
        {
          "system": "http://opencrvs.org/specs/id/statistical-code",
          "value": "ADMIN_STRUCTURE_dbTLdTi7s8F"
        },
        {
          "system": "http://opencrvs.org/specs/id/jurisdiction-type",
          "value": "STATE"
        }
      ],
      "name": "Chuminga",
      "alias": [
        "Chuminga"
      ],
      "description": "dbTLdTi7s8F",
      "status": "active",
      "mode": "instance",
      "partOf": {
        "reference": "Location/0"
      },
      "type": {
        "coding": [
          {
            "system": "http://opencrvs.org/specs/location-type",
            "code": "ADMIN_STRUCTURE"
          }
        ]
      },
      "physicalType": {
        "coding": [
          {
            "code": "jdn",
            "display": "Jurisdiction"
          }
        ]
      },
      "extension": [
        {
          "url": "http://hl7.org/fhir/StructureDefinition/location-boundary-geojson",
          "valueAttachment": {
            "contentType": "application/geo+json",
            "data": "<base64>"
          }
        }
      ],
      "id": "5752e89e-29b8-4e5f-b413-ee8fd8532c1f"
    }
  ]
}